zipfile2/__init__.py
zipfile2/_lean_zipfile.py
zipfile2/_version.py
zipfile2/_zipfile.py
zipfile2/common.py
zipfile2/tests/__init__.py
zipfile2/tests/common.py
zipfile2/tests/test__lean_zipfile.py
zipfile2/tests/test__zipfile.py
zipfile2/tests/data/nose.egg
zipfile2/tests/data/vtk.egg
zipfile2/tests/data/zip_with_directory_softlink.zip
zipfile2/tests/data/zip_with_permissions.zip
zipfile2/tests/data/zip_with_softlink.zip
zipfile2/tests/data/zip_with_softlink_and_permissions.zip
zipfile2-0.0.12.dist-info/DESCRIPTION.rst
zipfile2-0.0.12.dist-info/METADATA
zipfile2-0.0.12.dist-info/RECORD
zipfile2-0.0.12.dist-info/WHEEL
zipfile2-0.0.12.dist-info/metadata.json
zipfile2-0.0.12.dist-info/top_level.txt
