Metadata-Version: 1.1
Name: zipfile2
Version: 0.0.12
Summary: An improved ZipFile class.
Home-page: UNKNOWN
Author: David Cournapeau
Author-email: cournape@gmail.com
License: PSFL
Platform: UNKNOWN
Classifier: Development Status :: 3 - Alpha
Classifier: License :: OSI Approved :: Python Software Foundation License
Classifier: Operating System :: OS Independent
Classifier: Programming Language :: Python :: 2.6
Classifier: Programming Language :: Python :: 2.7
Classifier: Programming Language :: Python :: 3.3
Classifier: Programming Language :: Python :: 3.4
